marinator/__init__.py
marinator/__main__.py
marinator/base.py
marinator-0.2.6.dist-info/METADATA
marinator-0.2.6.dist-info/WHEEL
marinator-0.2.6.dist-info/top_level.txt
marinator-0.2.6.dist-info/RECORD
