Metadata-Version: 2.1
Name: marinator
Version: 0.2.6
Summary: The power of a Marina for everyone
Home-page: https://github.com/joamag/marinator
Author: João Magalhães
Author-email: joamag@gmail.com
License: Apache License, Version 2.0
Keywords: ripe api
Platform: UNKNOWN
Classifier: Development Status :: 5 - Production/Stable
Classifier: Topic :: Utilities
Classifier: License :: OSI Approved :: Apache Software License
Classifier: Operating System :: OS Independent
Classifier: Programming Language :: Python
Classifier: Programming Language :: Python :: 2.6
Classifier: Programming Language :: Python :: 2.7
Classifier: Programming Language :: Python :: 3.0
Classifier: Programming Language :: Python :: 3.1
Classifier: Programming Language :: Python :: 3.2
Classifier: Programming Language :: Python :: 3.3
Classifier: Programming Language :: Python :: 3.4
Classifier: Programming Language :: Python :: 3.5
Classifier: Programming Language :: Python :: 3.6
Classifier: Programming Language :: Python :: 3.7
Requires-Dist: appier
Requires-Dist: appier-console
Requires-Dist: ripe-api
Requires-Dist: PyPDF2
